triton/__init__.py
triton/_filecheck.py
triton/_internal_testing.py
triton/_utils.py
triton/errors.py
triton/knobs.py
triton/testing.py
triton/windows_utils.py
triton/_C/libtriton.pyd
triton/backends/__init__.py
triton/backends/compiler.py
triton/backends/driver.py
triton/backends/amd/__init__.py
triton/backends/amd/compiler.py
triton/backends/amd/driver.c
triton/backends/amd/driver.py
triton/backends/amd/lib/asanrtl.bc
triton/backends/amd/lib/ockl.bc
triton/backends/amd/lib/ocml.bc
triton/backends/nvidia/__init__.py
triton/backends/nvidia/compiler.py
triton/backends/nvidia/driver.c
triton/backends/nvidia/driver.py
triton/backends/nvidia/bin/ptxas.exe
triton/backends/nvidia/include/cuda.h
triton/backends/nvidia/lib/libdevice.10.bc
triton/backends/nvidia/lib/x64/cuda.lib
triton/compiler/__init__.py
triton/compiler/code_generator.py
triton/compiler/compiler.py
triton/compiler/errors.py
triton/compiler/make_launcher.py
triton/experimental/__init__.py
triton/experimental/gluon/__init__.py
triton/experimental/gluon/_compiler.py
triton/experimental/gluon/_runtime.py
triton/experimental/gluon/amd/__init__.py
triton/experimental/gluon/amd/gfx1250.py
triton/experimental/gluon/language/__init__.py
triton/experimental/gluon/language/_core.py
triton/experimental/gluon/language/_layouts.py
triton/experimental/gluon/language/_math.py
triton/experimental/gluon/language/_semantic.py
triton/experimental/gluon/language/_standard.py
triton/experimental/gluon/language/amd/__init__.py
triton/experimental/gluon/language/amd/_layouts.py
triton/experimental/gluon/language/amd/_ops.py
triton/experimental/gluon/language/amd/cdna3/__init__.py
triton/experimental/gluon/language/amd/cdna4/__init__.py
triton/experimental/gluon/language/amd/cdna4/async_copy.py
triton/experimental/gluon/language/amd/gfx1250/__init__.py
triton/experimental/gluon/language/amd/gfx1250/async_copy.py
triton/experimental/gluon/language/amd/gfx1250/mbarrier.py
triton/experimental/gluon/language/amd/gfx1250/tdm.py
triton_windows-3.6.0.post25.dist-info/licenses/LICENSE
triton_windows-3.6.0.post25.dist-info/METADATA
triton_windows-3.6.0.post25.dist-info/WHEEL
triton_windows-3.6.0.post25.dist-info/entry_points.txt
triton_windows-3.6.0.post25.dist-info/top_level.txt
triton_windows-3.6.0.post25.dist-info/RECORD
